[
  {
    "thirukkural": [
      {
        "id":1,
        "tamil_1":"அகர முதல எழுத்தெல்லாம் ஆதி",
        "tamil2":"பகவன் முதற்றே உலகு",
        "english":"",
        "kural": 1
      },
      {
        "id":2,
        "tamil":"",
        "english":"",
        "kural": 1
      },
      {
        "id":3,
        "tamil":"",
        "english":"",
        "kural": 1
      },
      {
        "id":4,
        "tamil":"",
        "english":"",
        "kural": 1
      },
      {
        "id":5,
        "tamil":"",
        "english":"",
        "kural": 1
      },
      {
        "id":6,
        "tamil":"",
        "english":"",
        "kural": 1
      },
      {
        "id":7,
        "tamil":"",
        "english":"",
        "kural": 1
      },
      {
        "id":8,
        "tamil":"",
        "english":"",
        "kural": 1
      },
      {
        "id":9,
        "tamil":"",
        "english":"",
        "kural": 1
      },
      {
        "id":10,
        "tamil":"",
        "english":"",
        "kural": 1
      },
      {
        "id":11,
        "tamil":"",
        "english":"",
        "kural": 1
      },
      {
        "id":12,
        "tamil":"",
        "english":"",
        "kural": 1
      },
      {
        "id":13,
        "tamil":"",
        "english":"",
        "kural": 1
      },
      {
        "id":14,
        "tamil":"",
        "english":"",
        "kural": 1
      },
      {
        "id":15,
        "tamil":"",
        "english":"",
        "kural": 1
      },
      {
        "id":16,
        "tamil":"",
        "english":"",
        "kural": 1
      }
    ]
  }
]